utilitilib/__init__.py
utilitilib/arrays/__init__.py
utilitilib/arrays/chunk_list.py
utilitilib/arrays/remove_all.py
utilitilib/arrays/remove_duplicate.py
utilitilib/arrays/shuffle.py
utilitilib/arrays/unique_value_counter.py
utilitilib/dateandtime/__init__.py
utilitilib/dateandtime/days_between_dates.py
utilitilib/math/__init__.py
utilitilib/math/mean.py
utilitilib/math/median.py
utilitilib/math/mode.py
utilitilib/math/range.py
utilitilib/strings/__init__.py
utilitilib/strings/are_anagrams.py
utilitilib/strings/censor_string.py
utilitilib/strings/format_num.py
utilitilib/strings/remove_whitespace.py
utilitilib/strings/replace_one.py
utilitilib/strings/to_title_case.py
utilitilib-0.0.3.dist-info/LICENSE
utilitilib-0.0.3.dist-info/METADATA
utilitilib-0.0.3.dist-info/WHEEL
utilitilib-0.0.3.dist-info/top_level.txt
utilitilib-0.0.3.dist-info/RECORD
