Metadata-Version: 2.1
Name: utilitilib
Version: 0.0.3
Summary: A python utility package that provides commonly used functionalities or helper methods.
Home-page: https://github.com/oDqnger/utilitilib
Author: Diman Gal Henege
Author-email: dimanchansilu@gmail.com
License: MIT License
Keywords: python,helper,functions,utility,utilities,algorithms,data types
Classifier: Development Status :: 5 - Production/Stable
Classifier: Intended Audience :: Developers
Classifier: License :: OSI Approved :: MIT License
Classifier: Programming Language :: Python :: 3.0
License-File: LICENSE
